{
  "$schema": "https://static.modelcontextprotocol.io/schemas/2025-12-11/server.schema.json",
  "name": "io.github.holco-apps/pennypilot",
  "title": "PennyPilot",
  "description": "Copilote IA pour cabinets Pennylane. Note de synthèse mensuelle en 8 s, 1h30/dossier économisé.",
  "repository": {
    "url": "https://github.com/holco-apps/pennypilot",
    "source": "github"
  },
  "websiteUrl": "https://apps.holco.co/mcp/pennylane",
  "version": "0.2.2",
  "packages": [
    {
      "registryType": "mcpb",
      "identifier": "https://github.com/holco-apps/pennypilot/releases/download/v0.2.2/pennypilot-0.2.2.mcpb",
      "fileSha256": "2ed39233dc8d6b5bcdb2d46b184a335eaee18f3d00b271af50741cbcfa10bbd3",
      "version": "0.2.2",
      "transport": {
        "type": "stdio"
      }
    }
  ]
}